mppt/__init__.py
mppt/hello.py
mppt/py.typed
mppt/sort.py
mppt-0.8.0.dist-info/licenses/LICENSE
mppt-0.8.0.dist-info/METADATA
mppt-0.8.0.dist-info/WHEEL
mppt-0.8.0.dist-info/top_level.txt
mppt-0.8.0.dist-info/zip-safe
mppt-0.8.0.dist-info/RECORD
