Metadata-Version: 2.4
Name: mppt
Version: 0.8.0
Summary: A Modern Python Package Template
Author-email: Xiangzhuang Shen <datahonor@gmail.com>
License-Expression: MIT
Project-URL: Homepage, https://shenxiangzhuang.github.io/mppt
Project-URL: Bug Tracker, https://shenxiangzhuang.github.io/mppt/issues
Project-URL: Documentation, https://shenxiangzhuang.github.io/mppt
Project-URL: Source Code, https://github.com/shenxiangzhuang/mppt
Project-URL: Release Notes, https://shenxiangzhuang.github.io/mppt/changelog/
Classifier: Development Status :: 3 - Alpha
Classifier: Intended Audience :: Science/Research
Classifier: Intended Audience :: Developers
Classifier: Operating System :: OS Independent
Classifier: Programming Language :: Python :: 3.12
Classifier: Programming Language :: Python :: 3.13
Classifier: Programming Language :: Python :: 3.14
Requires-Python: >=3.12
License-File: LICENSE
Dynamic: license-file
